llmlayer/__init__.py
llmlayer/_version.py
llmlayer/client.py
llmlayer/config.py
llmlayer/exceptions.py
llmlayer/models.py
llmlayer-0.2.6.dist-info/METADATA
llmlayer-0.2.6.dist-info/WHEEL
llmlayer-0.2.6.dist-info/licenses/LICENSE
llmlayer-0.2.6.dist-info/RECORD
