Metadata-Version: 2.4
Name: llmlayer
Version: 0.2.6
Summary: Official Python SDK for the LLMLayer Search & Answer API
Project-URL: Homepage, https://github.com/YassKhazzan/llmlayer_python
Project-URL: Issues, https://github.com/YassKhazzan/llmlayer_python/issues
Author-email: Yassine Khazzan <yassine@llmlayer.ai>
License: MIT
License-File: LICENSE
Classifier: License :: OSI Approved :: MIT License
Classifier: Operating System :: OS Independent
Classifier: Programming Language :: Python :: 3
Requires-Python: >=3.9
Requires-Dist: httpx>=0.28.1
Requires-Dist: pydantic>=2.6
